comparator_1bit.v
// module comparator_8bit(AeqB, AgtB, AltB, A, B, msb_signed);
	
// 	output wire AeqB, AgtB, AltB;
// 	input wire [7:0] A, B;
// 	input wire msb_signed;

// 	wire [7:0] AeqB_internal, AgtB_internal, AltB_internal;

// 	integer i;
// 	for(i = 0; i <=7; i=i+1)
// 	begin
// 		assign AeqB_internal[i] = ~(A[i]^B[i]);
// 		assign AgtB_internal[i] = A[i]&(~B[i]);
// 		assign AltB_internal[i] = (~A[i]&B[i]);
// 	end

// 	i = 7;
// 	while(AeqB_internal[i] == 1)
// 	begin
		
// 	end

// endmodule
`timescale 1ns/10ps

module tb_comparator_1bit();
	wire AeqB, AgtB, AltB;
	reg AeqB_LSB, AgtB_LSB, AltB_LSB, A, B;

	comparator_1bit uut(AeqB, AgtB, AltB, AeqB_LSB, AgtB_LSB, AltB_LSB, A, B);

	initial
	begin
		#00	AeqB_LSB = 1'b1; AgtB_LSB = 1'b0; AltB_LSB = 1'b0;
		#20 A = 1'b0; B = 1'b0;
		#20 A = 1'b0; B = 1'b1;
		#20 A = 1'b1; B = 1'b0;
		#20 A = 1'b1; B = 1'b1;

		#20	AeqB_LSB = 1'b0; AgtB_LSB = 1'b1; AltB_LSB = 1'b0;
		#20 A = 1'b0; B = 1'b0;
		#20 A = 1'b0; B = 1'b1;
		#20 A = 1'b1; B = 1'b0;
		#20 A = 1'b1; B = 1'b1;

		#20	AeqB_LSB = 1'b0; AgtB_LSB = 1'b0; AltB_LSB = 1'b1;
		#20 A = 1'b0; B = 1'b0;
		#20 A = 1'b0; B = 1'b1;
		#20 A = 1'b1; B = 1'b0;
		#20 A = 1'b1; B = 1'b1;

		#20 $stop;
	end
	
	initial
	begin
		$monitor("time=%3d, AeqB=%b, AgtB=%b, AltB=%b, AeqB_LSB=%b, AgtB_LSB=%b, AltB_LSB=%b, A=%b, B=%b", $time, AeqB, AgtB, AltB, AeqB_LSB, AgtB_LSB, AltB_LSB, A, B);
	end

	initial
	begin
		$dumpfile("comparator_1bit.vcd");
		$dumpvars;
	end
endmodule
	


module comparator_1bit(AeqB, AgtB, AltB, AeqB_LSB, AgtB_LSB, AltB_LSB, A, B);
	
	output reg AeqB, AgtB, AltB;
	input wire AeqB_LSB, AgtB_LSB, AltB_LSB, A, B;

	wire AeqB_temp;
	assign AeqB_temp = ~(A^B);
	
	always@(*)
	begin
		if ((AeqB_temp == 1'b1)&&(AeqB_LSB == 1'b1))
		begin
			 AeqB = 1'b1;
			 AgtB = 1'b0;
			 AltB = 1'b0;
		end
		else if (AeqB_temp == 1'b1 && AgtB_LSB == 1'b1) 
		begin
			 AgtB = 1'b1;
			 AeqB = 1'b0;
			 AltB = 1'b0;
		end
		else if (AeqB_temp == 1'b1 && AltB_LSB == 1'b1) 
		begin
			 AltB = 1'b1;
			 AeqB = 1'b0;
			 AgtB = 1'b0;	
		end
		else if (A&(~B) == 1'b1)
		begin
			 AgtB = 1'b1;
			 AeqB = 1'b0;
			 AltB = 1'b0;
		end
		else 
		begin
			 AltB = 1'b1;	
			 AeqB = 1'b0;
			 AgtB = 1'b0;
		end
	end
endmodule

HW1/comparator_1bit.vcd
$date
	Fri Jan 19 00:25:30 2018
$end
$version
	Icarus Verilog
$end
$timescale
	10ps
$end
$scope module tb_comparator_1bit $end
$var wire 1 ! AeqB $end
$var wire 1 " AgtB $end
$var wire 1 # AltB $end
$var reg 1 $ A $end
$var reg 1 % AeqB_LSB $end
$var reg 1 & AgtB_LSB $end
$var reg 1 ' AltB_LSB $end
$var reg 1 ( B $end
$scope module uut $end
$var wire 1 ) A $end
$var wire 1 * AeqB_LSB $end
$var wire 1 + AeqB_temp $end
$var wire 1 , AgtB_LSB $end
$var wire 1 - AltB_LSB $end
$var wire 1 . B $end
$var reg 1 / AeqB $end
$var reg 1 0 AgtB $end
$var reg 1 1 AltB $end
$upscope $end
$upscope $end
$enddefinitions $end
#0
$dumpvars
11
00
0/
x.
0-
0,
x+
1*
x)
x(
0'
0&
1%
x$
1#
0"
0!
$end
#2000
01
0#
1/
1!
1+
0(
0.
0$
0)
#4000
0/
0!
11
1#
0+
1(
1.
#6000
01
0#
10
1"
0(
0.
1$
1)
#8000
1/
1!
1+
00
0"
01
0#
1(
1.
#10000
0/
0!
10
1"
1&
1,
0%
0*
#12000
0(
0.
0$
0)
#14000
00
0"
11
1#
0+
1(
1.
#16000
01
0#
10
1"
0(
0.
1$
1)
#18000
1+
10
1"
01
0#
1(
1.
#20000
00
0"
11
1#
1'
1-
0&
0,
#22000
0(
0.
0$
0)
#24000
0+
1(
1.
#26000
01
0#
10
1"
0(
0.
1$
1)
#28000
1+
00
0"
11
1#
1(
1.
